psstore4ru/__init__.py
psstore4ru/crawler.py
psstore4ru/enmasse.py
psstore4ru/games.py
psstore4ru/homepage.py
psstore4ru/tests.py
psstore4ru/utils.py
psstore4ru/variables.py
psstore4ru/core/__init__.py
psstore4ru/core/asynchronous.py
psstore4ru/core/deprecated.py
psstore4ru/core/scraping_routines/__init__.py
psstore4ru/core/scraping_routines/catalogue_page.py
psstore4ru/core/scraping_routines/game_page.py
psstore4ru/core/scraping_routines/meta/__init__.py
psstore4ru/core/scraping_routines/meta/variables.py
psstore4ru/core/scraping_routines/utils/__init__.py
psstore4ru/core/scraping_routines/utils/reusable.py
psstore4ru/usage/__init__.py
psstore4ru/usage/showcase.py
psstore_ru-2.0.0.dist-info/LICENSE
psstore_ru-2.0.0.dist-info/METADATA
psstore_ru-2.0.0.dist-info/WHEEL
psstore_ru-2.0.0.dist-info/top_level.txt
psstore_ru-2.0.0.dist-info/RECORD
