Metadata-Version: 2.1
Name: psstore-ru
Version: 2.0.0
Summary: Play Station Store Russian Python Interface
Home-page: https://github.com/Ian-Gabaraev/psstorereader
Author: Ian Gabaraev
Author-email: hrattisianees@gmail.com
License: UNKNOWN
Platform: UNKNOWN
Classifier: Programming Language :: Python :: 3
Classifier: License :: OSI Approved :: MIT License
Classifier: Operating System :: OS Independent
Requires-Python: >=3.6
Requires-Dist: requests
Requires-Dist: bs4
Requires-Dist: pyyaml
Requires-Dist: asyncio
Requires-Dist: aiohttp
